fhir_tools/__init__.py
fhir_tools/definitions/v4/generated/resources.json
fhir_tools/definitions/v4/generated/types.json
fhir_tools/generation.py
fhir_tools/readers.py
fhir_tools/resources.py
fhir_tools/utils.py
fhir_tools-0.1.4.dist-info/LICENSE
fhir_tools-0.1.4.dist-info/WHEEL
fhir_tools-0.1.4.dist-info/METADATA
fhir_tools-0.1.4.dist-info/RECORD
