Metadata-Version: 2.1
Name: fhir-tools
Version: 0.1.4
Summary: Toolbox for working with FHIR Resources and Types
Home-page: https://github.com/blanebf/fhir_tools
License: MIT
Keywords: medical,fhir,tools
Author: Pavel 'Blane' Tuchin
Author-email: blane.public@gmail.com
Requires-Python: >=2.7, !=3.0.*, !=3.1.*, !=3.2.*, !=3.3.*, !=3.4.*, !=3.5.*, !=3.6.*
Classifier: Development Status :: 3 - Alpha
Classifier: License :: OSI Approved :: MIT License
Classifier: Programming Language :: Python :: 2
Classifier: Programming Language :: Python :: 2.7
Classifier: Programming Language :: Python :: 3
Classifier: Programming Language :: Python :: 3.7
Classifier: Topic :: Software Development :: Libraries
Requires-Dist: six
Project-URL: Repository, https://github.com/blanebf/fhir_tools
